{"status":"ok","totalResults":26,"articles":[{"source":{"id":null,"name":"Yicai.com"},"author":null,"title":"美股交易员：股市反弹令鲍威尔“变脸”，静待连续加息50个基点 - 一财网","description":"纽交所交易员塔奇曼认为，让鲍威尔“变脸”的是美股反应。","url":"https://www.yicai.com/news/101357764.html","urlToImage":null,"publishedAt":"2022-03-23T02:17:55Z","content":null},{"source":{"id":null,"name":"Xnnews.com.cn"},"author":"咸宁网","title":"俄乌冲突持续欧盟能源出路在何方- 咸宁网 - 咸宁新闻网新闻频道","description":"俄乌冲突持续欧盟能源出路在何方新华社记者近期,俄乌冲突导致的供应不确定性进一步加剧欧洲能源困境，也给亟待摆脱新冠疫情困扰的欧洲经济再度蒙上阴影。","url":"http://news.xnnews.com.cn/gjxw2/202203/t20220323_2567941.shtml","urlToImage":null,"publishedAt":"2022-03-23T01:57:00Z","content":": \r\nICP06018974 AVSP 2016019 42120202000014\r\nCopyright © 2005 - 2017 Xnnews.com.cn All Rights Reserved \r\nxnnews@163.com QQ67219397 42120180010"},{"source":{"id":null,"name":"Caacnews.com.cn"},"author":null,"title":"“3·21”东航飞行事故国家应急处置指挥部举行首场新闻发布会 - 中国民航新闻信息网","description":null,"url":"http://www.caacnews.com.cn/1/1/202203/t20220323_1341537.html","urlToImage":null,"publishedAt":"2022-03-23T01:16:00Z","content":"3·21MU5735\r\n3223·21\r\nMU57353211316141789001420142312393512015622898618239\r\n5\r\n1400678\r\n13200\r\n 3211550320322200\r\n9\r\n24123123\r\n160"},{"source":{"id":null,"name":"Sina.com.cn"},"author":"上海市纪委监委网站","title":"当前全国疫情处于高位平台阶段我国具备“动态清零”能力 - 瞭望东方周刊","description":"当前全国疫情处于高位平台阶段  我国具备“动态清零”能力","url":"https://news.sina.com.cn/c/2022-03-23/doc-imcwiwss7577086.shtml","urlToImage":"","publishedAt":"2022-03-23T00:43:46Z","content":null},{"source":{"id":null,"name":"Ln.gov.cn"},"author":null,"title":"辽宁省人民政府 - 中国辽宁","description":null,"url":"http://www.ln.gov.cn/ywdt/jrln/wzxx2018/202203/t20220323_4531271.html","urlToImage":null,"publishedAt":"2022-03-23T00:43:25Z","content":"3220-24367129134412753423211119\r\n32224148420710152467(44819)994784210"},{"source":{"id":null,"name":"Changzhou.gov.cn"},"author":null,"title":"哈焊华通挂牌上市创业板为常州今年首家、累计第82家上市企业 - 常州人民政府网","description":null,"url":"http://www.changzhou.gov.cn/ns_news/398164799363915","urlToImage":null,"publishedAt":"2022-03-23T00:41:44Z","content":"32282\r\n532301137IPO4545.3415.376.98199752015161122144106"},{"source":{"id":null,"name":"People.com.cn"},"author":"2173","title":"【奋进新征程建功新时代·伟大变革】水润华夏国家水安全保障能力全面提升--时政--人民网 - politics.people.com.cn","description":"今天（3月22日）是第三十个世界水日。党的十八大以来，习近平总书记深刻洞察我国国情水情，他指出，水安全是涉及国家长治久安的大事，全党要大力增强水忧患意识、水危机意识，从全面建成小康社会、实现中华民族永","url":"http://politics.people.com.cn/n1/2022/0323/c1001-32381752.html","urlToImage":null,"publishedAt":"2022-03-23T00:36:00Z","content":null},{"source":{"id":null,"name":"Bjx.com.cn"},"author":null,"title":"减少能源产业碳足迹！发改委、能源局印发《“十四五”现代能源体系规划》-北极星碳管家网 - 北极星电力新闻网","description":null,"url":"https://news.bjx.com.cn/html/20220323/1212098.shtml","urlToImage":null,"publishedAt":"2022-03-23T00:32:53Z","content":":322¼\r\nãõ \r\nã \r\n ú £\r\nµá\r\nú á2025ú 60ú80% ú \r\n úá\r\núá¿÷ òú¶¶ \r\núáú úúú 3.5\r\n ¯¯ã û\r\n£"},{"source":{"id":null,"name":"Sports.cn"},"author":null,"title":"新型场馆让冰雪运动不受季节限制 - sports.cn","description":"体育产业平台，推出体育产业专题，深入剖析体育产业现状，挖掘产业及其细分领域的投资机会，为投资者提供专业化研究报告、定制调研报告、项目计划、产业规划、招商策划等高品质服务。体育产业平台是体育产业首选资源交互平台,为各类体育组织、企业和个人提供体育信息交互、专业交流、赛事服务、远程培训、体育","url":"https://www.sports.cn/cydt/tycg/2022/0323/403039.html","urlToImage":null,"publishedAt":"2022-03-23T00:30:48Z","content":"3.46202110“”\r\n“”\r\n——31335001.680%\r\n“”——“”“”“”3\r\n“”7.52.568“”“”2.5“”“”60%“”"},{"source":{"id":null,"name":"People.com.cn"},"author":"105451","title":"三峡南线船闸提前恢复通航--新闻报道-中国共产党新闻网 - People","description":"图为3月22日拍摄的三峡五级船闸。　　郑家裕摄（人民视觉）据新华社武汉3月22日电  （记者李思远）记者从长江三峡通航管理局获悉：22日20时，三峡南线船闸2022年计划性停航检修,三峡南线船闸提前恢复通航--新闻报道","url":"http://cpc.people.com.cn/n1/2022/0323/c64387-32381615.html","urlToImage":null,"publishedAt":"2022-03-23T00:22:00Z","content":null},{"source":{"id":null,"name":"Southcn.com"},"author":"石瑾瑜","title":"CBA | 常规赛收官季后赛首轮对阵出炉_南方网 - 体育","description":"季后赛将于4月1日起在江西省南昌市举行。","url":"https://sports.southcn.com/node_3ccf0aeb7c/55672a17cc.shtml","urlToImage":null,"publishedAt":"2022-03-23T00:21:00Z","content":"CBA226111:110\r\n2212118:84134:9097:80151:128\r\n119:1241110.8111:11011\r\n12415-12"},{"source":{"id":null,"name":"Xmnn.cn"},"author":null,"title":"备战12强赛教练肇俊哲：对阵沙特国足以我为主_新闻中心 - 厦门网","description":"阿联酋当地时间20日18点30分，中国男足国家队在沙迦进行了训练。助理教练肇俊哲接受采访时表示，对阵沙特的比赛，国足要以我为主，最后两场比赛，也要给大家带来希望。","url":"https://news.xmnn.cn/xmnn/2022/03/23/101021169.shtml","urlToImage":null,"publishedAt":"2022-03-23T00:16:00Z","content":""},{"source":{"id":null,"name":"Hangzhou.com.cn"},"author":"汪浩","title":"《新蝙蝠侠》市场遇冷上映五天未破亿，难接地气？-杭州新闻中心-杭州网 - 杭州网","description":"低迷的三月影市，迎来了又一部被冠以“救市主”的大片——《新蝙蝠侠》。然而开局五天，《新蝙蝠侠》虽然口碑良好，豆瓣评分7.7，却至今仍未破亿。截至3月22日晚7点40分，《新蝙蝠侠》全国总票房为8491.2万。","url":"https://hznews.hangzhou.com.cn/wenti/content/2022-03/23/content_8206721.htm","urlToImage":null,"publishedAt":"2022-03-22T23:35:00Z","content":"7.73227408491.2\r\n175\r\nDCDCDC\r\n22923.4\r\n357926161439.12014322740954.59\r\n·IP\r\nB2-20110366 | 1105105 | 33120170003:[2021]1187-055 | ICP11041366-1 |  33010002000058()Copyright © 2001 - 2019 Hangzhou.com.… [+25 chars]"},{"source":{"id":null,"name":"Www.ce.cn"},"author":"孙丹","title":"中办国办军办：坚决依法打击歪曲、丑化、亵渎、否定英烈事迹和精神的言行 - 中国经济网","description":null,"url":"http://www.ce.cn/xwzx/gnsz/gdxw/202203/23/t20220323_37425687.shtml","urlToImage":null,"publishedAt":"2022-03-22T23:22:00Z","content":null},{"source":{"id":null,"name":"中国日报"},"author":"刁云娇","title":"复星医药进入新冠口服药Paxlovid“特仿”名单 - China Daily","description":"此次许可下，相关产品的生产设施需经严格监管机构批准，或经世界卫生组织资格预审合格。","url":"http://caijing.chinadaily.com.cn/a/202203/23/WS623a6cf2a3101c3ee7acce58.html","urlToImage":"http://img3.chinadaily.com.cn/images/202203/23/623a6dafa3101c3e686b026f.jpeg","publishedAt":"2022-03-22T23:17:00Z","content":null},{"source":{"id":null,"name":"Sina.com.cn"},"author":"市场资讯","title":"黑匣子还没找到，但关于黑匣子的14个关键问题有了答案！ - Sina.cn","description":"黑匣子还没找到，但关于黑匣子的14个关键问题有了答案！","url":"https://finance.sina.com.cn/jjxw/2022-03-23/doc-imcwiwss7561178.shtml","urlToImage":"//n.sinaimg.cn/spider20220323/280/w690h390/20220323/da02-1670065c21d8ad3d19a8553d4ba35974.jpg","publishedAt":"2022-03-22T22:47:24Z","content":null},{"source":{"id":null,"name":"Wallstreetcn.com"},"author":null,"title":"乌克兰农业部长：“欧洲粮仓”春季粮食播种面积预期被砍掉一半 - 华尔街见闻","description":null,"url":"https://wallstreetcn.com/livenews/2153931","urlToImage":null,"publishedAt":"2022-03-22T19:44:07Z","content":null},{"source":{"id":null,"name":"Stcn.com"},"author":"梅双","title":"复星医药2021年净利47.35亿元创新产品收入占比持续提升 - 证券时报","description":"复星医药(600196)3月22日晚间披露年报，2021年公司实现营业收入390.05亿元，同比增长28.70%；净利润47.35亿元，同比增长29.28%；扣非净利润32.77亿元，同比增长20.60%；经营活动产生的现金流量净额39.49亿元，同比增长53.07%。基本每股收益1.85元。公司拟每10股派发现金红利5.60元（税前）。","url":"http://www.stcn.com/company/gsxw/202203/t20220322_4268965.html","urlToImage":null,"publishedAt":"2022-03-22T14:02:00Z","content":"(600196)3222021390.0528.70%47.3529.28%32.7720.60%39.4953.07%1.85105.60\r\n2021289.0459.3841.18\r\n49.7524.28%38.3437.17%\r\n44.8622.23%15.52%33.598.9136.10%11.62%\r\n280015007.85%240\r\nmRNA202125%\r\n16.90125.3… [+131 chars]"},{"source":{"id":null,"name":"Xhby.net"},"author":null,"title":"以快制快干净彻底阻断疫情传播链条省疫情联防联控指挥部召开会议_新华报业网 - 新华报业网","description":"以快制快干净彻底阻断疫情传播链条 省疫情联防联控指挥部召开会议","url":"http://www.xhby.net/js/sz/202203/t20220322_7474215.shtml","urlToImage":null,"publishedAt":"2022-03-22T12:38:00Z","content":null},{"source":{"id":null,"name":"Workercn.cn"},"author":"迟语洋","title":"习近平总书记关切事丨华北地下水“大漏斗”修复进行时-学习进行时 - 中工网","description":"习近平总书记关切事丨华北地下水“大漏斗”修复进行时——地下水,超采,治理","url":"http://www.workercn.cn/34192/202203/22/220322183527616.shtml","urlToImage":null,"publishedAt":"2022-03-22T10:35:27Z","content":"· \r\n322\r\n322\r\n20143\r\n8\r\n7140\r\n1203500125\r\n2021512\r\n75%7\r\n20165\r\n202113\r\n1300120030\r\n319\r\n2020\r\n1/7\r\n2014\r\n20\r\n35502872\r\n2021917\r\n8651007.92\r\n3192021\r\n20\r\n2017223\r\n170275710\r\n101.9\r\n318\r\n70140\r\n2.4280… [+18 chars]"}]}