{"status":"ok","totalResults":34,"articles":[{"source":{"id":null,"name":"Seoul.co.kr"},"author":"https://www.seoul.co.kr","title":"'4골' 손흥민, EPL 파워랭킹 115위→1위 수직 상승 - 서울신문","description":"지난 주말 잉글랜드 프로축구 프리미어리그(EPL) 2라운드 경기에서 4골을 터뜨린 손흥민(토트넘)이 EPL 파워랭킹에서도 1위에 올랐다.영국 스카이스포츠가 22일 공개한 EPL 파워랭킹에서 손흥민은 8929점을 받아 1위를 차지했다. 지난주 1라운드 파워랭킹 집계 때는 115위(547점)였으나 수직 상승 했다. 이제 리그 초반으로 중간 집계이지만 ...","url":"https://www.seoul.co.kr/news/newsView.php?id=20200922500222","urlToImage":"https://img.seoul.co.kr/img/upload/2020/09/21/SSI_20200921155629.jpg","publishedAt":"2020-09-22T22:30:00Z","content":"..EPL BBC 2 11 \r\n(EPL) 2 4 () EPL 1 . 22 EPL 8929 1 . 1 115(547) . EPL 1 . 4 5-2 1 . 4 4 .EPL 1 -() 8642 2 . () 3(6568), () 4(6137) . 4 1 8(5592).\r\n, BBC 2 11 .\r\nicarus@seoul.co.kr"},{"source":{"id":null,"name":"Joins.com"},"author":"이해준","title":"아직 여성은 달에 못 갔다… 미국 \"32조 투입 보내겠다\" - 중앙일보 - 중앙일보","description":"미국 항공우주국(NASA)가 50년 만에 다시 달에 인류를 보내는 프로젝트를 계획하고 있다. 이번 프로젝트를 위한 예산은 차세대 대형 로켓인 '우주발사시스템'(SLS) 개발, 유인 우주선 '오리온'과 달 착륙선 개발 등에 쓰일 예정이라고 밝혔다.' . 이번 프로젝트는 2021년 11월 달궤도 무인 비행, 2023년 달 궤도 유인 비행, - 아르테미스 프로젝트,이번 프로젝트,착륙선 개발","url":"https://news.joins.com/article/23878672","urlToImage":"https://pds.joins.com/news/component/htmlphoto_mmdata/202009/23/443c1406-8021-40ec-aba1-81f09c518c99.jpg","publishedAt":"2020-09-22T22:12:22Z","content":"1972 . . [NASA]\r\n(NASA) 50 . ' ' '' . .    AFP 22 NASA .   NASA \" 4 280 (324800) \" . 2024 1 . 1972 . 50 . .   ''(SLS) , '' .' .   2021 11  , 2023 , 2024 .   lee.hayjune@joongang.co.kr"},{"source":{"id":null,"name":"Chosun.com"},"author":null,"title":"머스크 “한달만 기다려라, 완전 자율주행차 선보일 것” - 조선일보","description":"이날 머스크는 검은색 티셔츠와 청바지를 입고 연단에 등장했다. 그는 “우리는 아직 저렴한(affordable) 차량은 없다”면서도 “미래에는 갖게 될 것”이라고 했다. 다만 머스크는 “최근 배터리 가격을 낮췄다”고 덧붙였다. 테슬라는 LG화학과 중국 CATL, 일본 파나소닉으로부터 배터리를 공급받고 있으며, 독일에 자체 배터리 공장을 설립 중이다.","url":"https://www.chosun.com/international/us/2020/09/23/7GB43MMFHNHCFF3IM33Z43SVVQ/","urlToImage":"https://images.chosun.com/resizer/o0MPOAnV-qEYZ9BjfHsafrF83Dk=/1200x630/filters:focal(858x176:868x186)/cloudfront-ap-northeast-1.images.arcpublishing.com/chosun/ABK2BUHKEBH2FBZLI3THOJYKWE.gif","publishedAt":"2020-09-22T22:05:00Z","content":"3( ) ./AP \r\n(CEO) .\r\n , 22( ) . .\r\n . (affordable) . . LG CATL, , .\r\n 240 . . 27 .\r\n, 25.16(5.6%) 424.23 ."},{"source":{"id":null,"name":"Chosun.com"},"author":null,"title":"황재근X전영미, '비스'는 사랑을 싣고..김정난오정연도 놀란 '러브라인' [어저께TV] - 조선일보","description":"패션디자이너 황재근과 개그우먼 전영미가 오랜 우정 뒤에 싹튼 '러브라인'을 공개했다.지난 22일 오후 방송된 MBC every1 '비디오스타'는 '오! 재미난 인생 Love Myself' 특집으로 꾸며진 가운데 김정난, 황재근, 전영미, 오정연이 게스트로 출연했다.이날 '비디오스타' 황재근은 김정난, 전영미를 향해 각별한 애정을","url":"https://www.chosun.com/entertainments/entertain_photo/2020/09/23/PGCA4GZKY44XVFTT5GYN64XW3Y/","urlToImage":"https://images.chosun.com/resizer/gJLfknz0WIAjd3LcdriZHlH7u1E=/530x278/smart/cloudfront-ap-northeast-1.images.arcpublishing.com/chosun/V3YFFGVDXEFVCMYWG62AIOE2W4.jpg","publishedAt":"2020-09-22T22:00:00Z","content":".\r\n 22 MBC every1 '' '! Love Myself' , , , .\r\n '' , . \" '' OK \" \" 3 . 4~5 \" \" . \" .\r\n . . \" ' ' . ' ' ?\" .\r\n '' . \" \" \" . \" . \" ? ?\" .\r\n . '' \" \" \" . . \" . \" . \" .\r\n . \" . \" '' . \" ?\" \" \" . \" \" \" \" .… [+53 chars]"},{"source":{"id":"google-news","name":"Google News"},"author":null,"title":"[날씨] 오늘도 일교차 큰 가을 날씨...동해안·제주 비 / YTN - YTN news","description":null,"url":"https://news.google.com/__i/rss/rd/articles/CBMiK2h0dHBzOi8vd3d3LnlvdXR1YmUuY29tL3dhdGNoP3Y9TmdDb1J4SFdBQlHSAQA?oc=5","urlToImage":null,"publishedAt":"2020-09-22T21:47:08Z","content":null},{"source":{"id":null,"name":"Mt.co.kr"},"author":"이은","title":"'이남용♥' 허윤아, 실검 1위에…\"앞치마라도 입어볼게요\" - 머니투데이","description":"그룹 LPG 출신 가수 허윤아가 실시간 검색어 1위에 오른 소감을 전했다.허윤아는 지난 22일 자신의 인스타그램을 통해 포털 사이트 실시간 검색어에 오른 자신의 이름을...","url":"https://news.mt.co.kr/mtview.php?no=2020092306341395018","urlToImage":"https://thumb.mt.co.kr/21/2020/09/2020092306341395018_1.jpg","publishedAt":"2020-09-22T21:42:09Z","content":"<table><tr><td> LPG 1 .22 \" , . 1 . !\" .\r\n\"# # # # #\" .\r\n21 A ' ' . \r\n\" \" \" , \" \" \" . \" .\r\n.\r\n2005 LPG . \r\n</td></tr>\r\n</table>"},{"source":{"id":null,"name":"Mbn.co.kr"},"author":"노기완","title":"‘팔테어’ NC 알테어, 클린업보다 더 무섭네 [MK시선] - MBN","description":"매경닷컴 MK스포츠 노기완 기자그야말로 클린업보다 더 무섭다. 8번타자 애런 알테어(29·NC다이노스)가 맹...","url":"https://mbn.co.kr/news/sports/4289243","urlToImage":"http://img.mbn.co.kr/filewww/news/other/2020/09/23/062002000200.jpg","publishedAt":"2020-09-22T21:30:00Z","content":null},{"source":{"id":null,"name":"Hani.co.kr"},"author":null,"title":"쌍무기수·빗자루 도사·통일운동가 임동규 선생 별세 - 한겨레","description":"두차례 무기형 옥중에서 전통 복원 24반무예경당협회 총재로 널리 보급","url":"http://www.hani.co.kr/arti/society/obituary/963271.html","urlToImage":"http://flexible.img.hani.co.kr/flexible/normal/335/392/imgdb/original/2020/0923/20200923500143.jpg","publishedAt":"2020-09-22T21:27:12Z","content":null},{"source":{"id":null,"name":"Mt.co.kr"},"author":"광주=박수진","title":"브룩스 비보에 무거웠던 광주, KIA-키움 모두 애태운다 [★광주] - 머니투데이","description":"'All is well(모두 잘 될 거야).' 22일 KIA와 키움이 만났던 광주-기아 챔피언스필드는 무거운 공기로 가득했다. 경기를 앞두고 KIA 에이스 애런 브룩스(3...","url":"https://news.mt.co.kr/mtview.php?no=2020092215030073784","urlToImage":"https://thumb.mt.co.kr/21/2020/09/2020092215030073784_1.jpg","publishedAt":"2020-09-22T21:17:02Z","content":"'All is well( ).'22 KIA - . KIA (30) .\r\n. , . KIA .\r\n(55) KIA \" . . . ' ' . \" .\r\n. .\r\n, , KIA . 'All is well' .\r\nKIA . . 7 \" . . . \" ."},{"source":{"id":null,"name":"Mediadale.com"},"author":"김영애 기자","title":"겨울철 '코로나19 예방법' - 미디어데일","description":"차고 건조한 계절이 되면서 신종 코로나바이러스 감염증(코로나19)이 다시 급격히 확산될까 우려된다. 바이러스는 기온이 낮거나 건조한 환경에서 오래 살아남아 활발히 전파되기 때문이다. 특히 밀폐된 실내에서 공기 중 감염을 주의해야 한다.종합환경위생기업 세스코(대표이사 전찬혁)는 바이러스 생존력이 강해지는 가을·겨울을 맞아 ‘코로나19 바이러스가 살아남기 어려운 환경 조성 방법’을 22일 제시했다. 일상 속 감염 예방을 위한 습도 관리, 환기, 공기 살균, 소독 …","url":"http://www.mediadale.com/news/articleView.html?idxno=61330","urlToImage":"http://www.mediadale.com/news/thumbnail/202009/mn_61330_20200923060503_1_v150.jpg","publishedAt":"2020-09-22T21:05:00Z","content":"(19) . . .\r\n( ) · ‘19 ’ 22 . , , , .\r\n19 . 2m . . . 1m .\r\n1. … \r\n. . . .\r\n. . . . , .\r\n· . . 40~60% .\r\n2. “ · ”\r\n. . ·······PC··· . .\r\n. , . ‘’ 1 , 2 , 3 .\r\n3. \r\n. 19 UV-C . ‘UV ’ 24 1 , UV-C .\r\nUV-C… [+137 chars]"},{"source":{"id":null,"name":"Chosun.com"},"author":null,"title":"'공정경제 3법'만 문제가 아니다… 국회 개원 3개월 만에 기업규제 법안 284개 발의(대한상의 집계) - 조선비즈","description":"\"한 달만 일해도 퇴직금 준다고요? 기업은 봉입니까. 이러다 있던 일자리마저 없어집니다.\"지난 6월 이수진 더불어민주당 의원 등 17명이 근로자..","url":"https://biz.chosun.com/site/data/html_dir/2020/09/22/2020092202081.html","urlToImage":"https://image.chosun.com/sitedata/image/202009/22/2020092202064_0.jpg","publishedAt":"2020-09-22T21:00:00Z","content":"16 19 . 1 5 , .. , , . 3% . (032830)(005930) . \r\n. . 1 () 50%, 10% 14% , .\r\n\"19 \" .\r\n21 . \" () \" . 13 ."},{"source":{"id":null,"name":"Asiae.co.kr"},"author":"https://www.facebook.com/asiaeconomy","title":"'중견기업 디지털연대' 출범…디지털 전환 본격 추진 - 아시아경제","description":"산업통상자원부와 한국중견기업연합회는 23일 서울 더존을지타워에서 중견기업 주도의 디지털 전환 협력 및 확산을 위한 '중견기업 디지털연대' 출범식을 개최했다고 밝혔다. 행사는 세계적으로 디지털 전환이 경제·산업 전반에 급속히 확산되는 상황에서 역량 있는 수요·공급 중견기업이 협력해 '디지털 뉴딜'의 성공적인 추진을 뒷받침하기 위해 마련됐다. 앞서 지난달 발표된 '디지털 기반 산업혁신성","url":"https://www.asiae.co.kr/article/2020092306054802342","urlToImage":"https://cphoto.asiae.co.kr/listimglink/1/2020092306021697018_1600808537.jpg","publishedAt":"2020-09-22T20:33:00Z","content":"[ ] 23 ' ' .\r\n · · ' ' .\r\n ' ' .\r\n012510|103,0002,000-1.90%129,962105,0002020.09.22 15:30 (20), 12 3500.. -2.37% 1% , / 19.25% close\r\n, 11 .\r\n ' ' .\r\n=\r\n- .\r\n · .\r\n · , · · .\r\n · 20 3 150 .\r\n'- ' . ·… [+129 chars]"},{"source":{"id":null,"name":"Mk.co.kr"},"author":"stock.mk.co.kr","title":"코로나19로 지친 의료진 위로하는 멕시코 치료견 '애꾸눈 할리' - 매일경제","description":"주식시세,현재가,증권,종목,코스피,코스닥,뉴스,매일경제,매경,매일경제신문,신문,방송,매경인터넷,부동산,금융,mbn,만화,정치,사회,국제,매경이코노미,,주식,매매,돈,환율,주가,기업,벤처,중소기업,경영,기업,산업,창업,정부,정책,지식,비즈니스","url":"http://vip.mk.co.kr/news/view/21/21/3351848.html","urlToImage":null,"publishedAt":"2020-09-22T20:30:11Z","content":null},{"source":{"id":null,"name":"Nocutnews.co.kr"},"author":null,"title":"LG 공동 3위 이끈 채은성 \"한 번의 찬스 잘 잡아 기뻐\" - 노컷뉴스","description":"5회까지 지독하게도 점수를 내지 못했다. 프로야구 LG 트윈스는 22일 서울 잠실구장에서 열린 '2020 신한은행 SOL KBO 리그' SK 와이번스와 홈 경기에서 5회까지 0 대 2로 뒤지고 있었다. 올 시즌 상대 전적으로만 ..","url":"https://www.nocutnews.co.kr/news/5416999","urlToImage":"https://file2.nocutnews.co.kr/newsroom/image/2020/09/22/20200922220654737566_7_506_733.jpg","publishedAt":"2020-09-22T20:30:00Z","content":"LG 6 1 2 . (=)\r\n5 . LG 22 '2020 SOL KBO ' SK 5 0 2 . \r\nLG SK 112 . 3 2 . 2 5 . \r\nLG , . LG 6 1 1, 2 . 1 . \r\n. SK . 3 2 . LG 2 5 2 . \r\n8 1,3 1 . LG 4 1 3 SK 7 2 . \r\n\" \" \" \" .\r\n6 \" \" \" \" . \" \" .\r\nLG \" … [+37 chars]"},{"source":{"id":null,"name":"News1.kr"},"author":"(인천=뉴스1) 박아론 기자","title":"[오늘의 날씨]인천(23일, 수)…대체로 맑음, 일교차 커 - 뉴스1","description":"23일 인천 지역은 중국 북동지방에 위치한 고기압의 가장자리에 들어 대체로 맑겠다.수도권기상청 인천기상대에 따르면 이날 아침 최저기온은 강화군 12도, 계양구·서구 13도, 남동구·미추홀구·부평구·연수구 14도, 동구·중구 16도, 연수구 17도로 예상됐다.이날 낮 최저기온은 남동구·...","url":"https://www.news1.kr/articles/?4066874","urlToImage":"https://image.news1.kr/system/photos/2020/9/20/4391639/article.jpg","publishedAt":"2020-09-22T20:00:00Z","content":"23 .12, · 13, ··· 14, · 16, 17 .\r\n··· 24, ···· 23, 20 .\r\n0.5~1.0m .\r\n.\r\n\" \" \" , \" .\r\naron0317"},{"source":{"id":null,"name":"Voakorea.com"},"author":null,"title":"시진핑 주석 “코로나 사태 정치화 말아야” - 한국어 방송 - VOA Korean","description":"시진핑 중국 국가주석이 22일 신종 코로나바이러스 사태를 정치화 해서는 안된다고 말했습니다.\n\n시 주석은 이날 75차 유엔 총회 연설에서 전 세계가 중요한 기로에 서 있다며, 현시점에서 세계는 대결이 아닌 단합과 협력이 필요하다고 말했습니다. 그러면서 중국은 그 어떤 국가와 전쟁을 할 마음이 없다고 강조했습니다.  \n\n시 주석은 또 코로나 대응과 관련 “과학적인 지침을 따라야 하며, 세계보건기구(WHO)에 주도권을 줘야 한다”고 밝혔습니다.  \n\n그러면서 이 …","url":"https://www.voakorea.com/world/asia/xi-dont-politicize-covid19","urlToImage":"https://im-media.voltron.voanews.com/Drupal/01live-211/reuters-images/2020/09/reuters_com_2020_newsml_RC2R3J95E61O.jpg","publishedAt":"2020-09-22T19:45:00Z","content":"22 .\r\n 75 , .  .  \r\n , (WHO) .  \r\n , .\r\n  , , .  . \r\n . \r\nVOA"},{"source":{"id":null,"name":"Chosun.com"},"author":null,"title":"백신 대량유통 안해본 회사가 처음 맡아… 의료계 “정부, 낮은 단가 고집하다 사고” - 조선일보","description":"독감 백신이 부실 유통된 사태를 두고 의료계에서는 “정부의 부실 관리가 예견된 사고를 막지 못한 것”이라는 반응이 나왔다. 22일 질병관리청(질병청)에 따르면 올해 독감백신 공공물량을 유통한 신성약품은 35년 된 의약품 유통업체이나, 백신 유통을 맡은 건 이번이 처음이다. 전문가들은 “백신 유통을 처음 맡은 업체라면 정부가 더 체계적인 관리·감독을 해야 했다”고 지적했다.","url":"https://www.chosun.com/national/welfare-medical/2020/09/23/E6GOIVAHIFF4THQYPF5U2DTTAU/","urlToImage":"/pf/resources/images/logo_chosun_200.png?d=131","publishedAt":"2020-09-22T18:00:00Z","content":"21 22 . 35 . · .\r\n . \" .\r\n 4 . 5 1 8620( ) . , .\r\n 1 12000~13000 8700 . 1 7980, 1 7900 .\r\n . . . \" ."},{"source":{"id":null,"name":"Chosun.com"},"author":null,"title":"文 “한반도 희망 가득했던 변화, 지금은 멈춰” - 조선일보","description":"문재인 대통령은 22일(현지 시각) 미국 뉴욕에서 화상으로 진행된 75차 유엔총회 기조연설에서 북한 문제와 관련, “국제사회의 지지와 협력이 계속된다면 한반도 비핵화와 항구적 평화가 반드시 이뤄질 수 있다고 변함없이 믿고 있다”며 “한반도 평화의 시작은 평화에 대한 서로의 의지를 확인할 수 있는 ‘한반도 종전선언’”이라고 했다. 문 대통령은 이날 뉴욕 현지에서 공개된 사전 녹화 영상에서 “지금도 한반도 평화는 아직 미완성 상태에 있고 희망 가득했던 변화도 중단…","url":"https://www.chosun.com/politics/blue_house/2020/09/23/KHSI4LX5R5AWFFGILA5IBY7UEU/","urlToImage":"https://images.chosun.com/resizer/1zulmR9fbRu9HnhM4KQvORLMP94=/1200x630/smart/cloudfront-ap-northeast-1.images.arcpublishing.com/chosun/R2LR2PDO5FADNNJAPI3H66IVMY.jpg","publishedAt":"2020-09-22T18:00:00Z","content":"22( ) 75 . /\r\n22( ) 75 . · (no deal) 1 . · . .\r\n . . , . 2018 9 . .\r\n21( ) 75 . . /EPA \r\n, , · . · , . . (DMZ) , . .\r\n , · . .\r\n . 4, 3 . 2017 , 2018 2019 .\r\n . , . .\r\n () . ."},{"source":{"id":null,"name":"Chosun.com"},"author":null,"title":"文대통령, 2년만에 다시 띄운 ‘종전선언’… “한반도 평화 아직 미완성” - 조선일보","description":"문재인 대통령은 22일(현지 시각) 미국 뉴욕에서 화상으로 진행된 제75차 유엔총회 기조연설에서 “국제사회의 지지와 협력이 계속된다면 한반도 비핵화와 항구적 평화가 반드시 이뤄질 수 있다”며 “한반도 평화의 시작은 평화에 대한 서로의 의지를 확인할 수 있는 ‘한반도 종전선언’”이라고 했다.","url":"https://www.chosun.com/politics/blue_house/2020/09/23/AX5DYPPWDFAQRAWF72JGWJ5GSM/","urlToImage":"https://images.chosun.com/resizer/1zulmR9fbRu9HnhM4KQvORLMP94=/1200x630/smart/cloudfront-ap-northeast-1.images.arcpublishing.com/chosun/R2LR2PDO5FADNNJAPI3H66IVMY.jpg","publishedAt":"2020-09-22T16:41:00Z","content":"2018 9 18 . 2019 . / \r\n22( ) 75 () .\r\n2 \r\n . 6 . , .\r\n · (no deal) 1 . .\r\n 2018 9 73 . /\r\n2018 9 . 2 .\r\n . 1 7 () . · . .\r\n··· \r\n , , · . · , .\r\n . , , . , , .\r\n 22( ) 75 . /\r\n, · . .\r\n , , . . 10 26… [+26 chars]"},{"source":{"id":null,"name":"Chosun.com"},"author":null,"title":"신성약품 회장 “백신 종이박스 땅바닥에 놓는 실수...정치권 연루설 사실무근” - 조선일보","description":"질병관리청 조사에서 부실 유통된 백신의 효능과 안전성에 문제가 있는 것으로 최종 확인될 경우 올해 국가접종용 독감백신 1259만명분 중 최대 500만분이 그대로 폐기될 수 있다. 이렇게 되면 신성약품도 법적 책임을 피할 수 없을 것이라는 전망이 나온다.김진문 신성약품 회장은 22일 밤 본지와의 전화 인터뷰에서 “용역을 준 백신 유통 업체가 운송하는 과정에서 일부 문제가 있었다”며 유통 과정에서 일부 문제가 있었던 점을 인정했다. 김 회장은 “국민께 송구하고 질…","url":"https://www.chosun.com/national/welfare-medical/2020/09/23/LQJW2U7LPZHQFJUMBAQLKNPWO4/","urlToImage":"https://images.chosun.com/resizer/MjAAresRQTQa9uU09csnV2MMbJw=/180x94/filters:focal(82x79:92x89)/cloudfront-ap-northeast-1.images.arcpublishing.com/chosun/IW66JXJP7RF35EIFNI2SXGS6IM.jpg","publishedAt":"2020-09-22T15:42:00Z","content":"22 2 . .\r\n . .\r\n 1259 500 . .\r\n 22 . .\r\nQ: .\r\n ( ): . . 1000 .\r\nQ: ?\r\n: . . . .\r\nQ: . A .\r\n: . . . A . .\r\nQ: .\r\n: . . 2~8 . , . . .\r\nQ. .\r\n: . . 11 . () 1 , . . .\r\nQ. ?\r\n: . 100 .\r\nQ, ?\r\n: 2~8 , . . … [+4 chars]"}]}